{
  "project_info": {
    "project_number": "848454495631",
    "project_id": "flutter-firebase-auth-exercise",
    "storage_bucket": "flutter-firebase-auth-exercise.firebasestorage.app"
  },
  "client": [
    {
      "client_info": {
        "mobilesdk_app_id": "1:848454495631:android:dbba13dcf1b528c5a06ffa",
        "android_client_info": {
          "package_name": "com.example.flutter_firebase_auth_complete"
        }
      },
      "oauth_client": [],
      "api_key": [
        {
          "current_key": "AIzaSyDMPb39mT5bLWNX1_ZXkrTbDtpiBI4HzUo"
        }
      ],
      "services": {
        "appinvite_service": {
          "other_platform_oauth_client": []
        }
      }
    }
  ],
  "configuration_version": "1"
}